{"type":"object","properties":{"queryTime":{"type":"number"},"pagination":{"type":"object","properties":{"limit":{"type":"number"},"offset":{"type":"number"},"total":{"type":"number"},"hasMore":{"type":"boolean"}},"required":["limit","offset","total","hasMore"]},"data":{"type":"array","items":{"type":"object","properties":{"id":{"type":"string","format":"uuid"},"foo_id":{"type":"string","format":"uuid"},"value":{"type":"integer"},"label":{"type":"string"},"notes":{"type":"string"},"is_enabled":{"type":"boolean"},"created_at":{"type":"string","format":"date-time"},"updated_at":{"type":"string","format":"date-time"},"_peerdb_synced_at":{"type":"string","format":"date-time"},"_peerdb_is_deleted":{"type":"integer"},"_peerdb_version":{"type":"integer"}},"required":["id","foo_id","value","is_enabled","created_at","updated_at","_peerdb_synced_at","_peerdb_is_deleted","_peerdb_version"],"x-readme-ref-name":"bar"}}},"required":["queryTime","pagination","data"],"x-readme-ref-name":"GetBarsWithCDCResponse"}